scrapy_redis_expand/RedisPipeline.py
scrapy_redis_expand/__init__.py
scrapy_redis_expand-1.1.1.dist-info/METADATA
scrapy_redis_expand-1.1.1.dist-info/WHEEL
scrapy_redis_expand-1.1.1.dist-info/top_level.txt
scrapy_redis_expand-1.1.1.dist-info/RECORD
