Metadata-Version: 2.1
Name: scrapy-redis-expand
Version: 1.1.1
Summary: scrapy redis 拓展
Home-page: 
Author: Iceland
Author-email: 1185330343@qq.com
